django_jsonplus/__init__.py
django_jsonplus/admin.py
django_jsonplus/apps.py
django_jsonplus/coders.py
django_jsonplus/models.py
django_jsonplus/views.py
django_jsonplus-0.1.3.dist-info/DESCRIPTION.rst
django_jsonplus-0.1.3.dist-info/METADATA
django_jsonplus-0.1.3.dist-info/RECORD
django_jsonplus-0.1.3.dist-info/WHEEL
django_jsonplus-0.1.3.dist-info/metadata.json
django_jsonplus-0.1.3.dist-info/top_level.txt
