Metadata-Version: 2.0
Name: django-jsonplus
Version: 0.1.3
Summary: Django extension for non-basic types' serialization to JSON via jsonplus lib.
Home-page: https://github.com/randomir/jsonplus/tree/master/python-django
Author: Radomir Stevanovic
Author-email: radomir.stevanovic@gmail.com
License: MIT
Platform: any
Classifier: Environment :: Web Environment
Classifier: Intended Audience :: Developers
Classifier: License :: OSI Approved :: MIT License
Classifier: Operating System :: OS Independent
Classifier: Programming Language :: Python
Classifier: Topic :: Internet :: WWW/HTTP :: Dynamic Content
Classifier: Topic :: Software Development :: Libraries :: Python Modules
Requires-Dist: Django (>=1.8)
Requires-Dist: jsonplus (>=0.8)
Requires-Dist: six
